flet/__init__.py
flet/ads/__init__.py
flet/app.py
flet/auth/__init__.py
flet/auth/authorization.py
flet/auth/group.py
flet/auth/oauth_provider.py
flet/auth/oauth_token.py
flet/auth/providers/__init__.py
flet/auth/providers/auth0_oauth_provider.py
flet/auth/providers/azure_oauth_provider.py
flet/auth/providers/github_oauth_provider.py
flet/auth/providers/google_oauth_provider.py
flet/auth/user.py
flet/canvas/__init__.py
flet/cli.py
flet/core/adaptive_control.py
flet/core/ads/banner.py
flet/core/ads/base_ad.py
flet/core/ads/interstitial.py
flet/core/ads/native.py
flet/core/alert_dialog.py
flet/core/alignment.py
flet/core/animated_switcher.py
flet/core/animation.py
flet/core/app_bar.py
flet/core/audio.py
flet/core/audio_recorder.py
flet/core/auto_complete.py
flet/core/autofill_group.py
flet/core/badge.py
flet/core/banner.py
flet/core/blur.py
flet/core/border.py
flet/core/border_radius.py
flet/core/bottom_app_bar.py
flet/core/bottom_sheet.py
flet/core/box.py
flet/core/button.py
flet/core/buttons.py
flet/core/canvas/arc.py
flet/core/canvas/canvas.py
flet/core/canvas/circle.py
flet/core/canvas/color.py
flet/core/canvas/fill.py
flet/core/canvas/line.py
flet/core/canvas/oval.py
flet/core/canvas/path.py
flet/core/canvas/points.py
flet/core/canvas/rect.py
flet/core/canvas/shadow.py
flet/core/canvas/shape.py
flet/core/canvas/text.py
flet/core/card.py
flet/core/charts/bar_chart.py
flet/core/charts/bar_chart_group.py
flet/core/charts/bar_chart_rod.py
flet/core/charts/bar_chart_rod_stack_item.py
flet/core/charts/chart_axis.py
flet/core/charts/chart_axis_label.py
flet/core/charts/chart_grid_lines.py
flet/core/charts/chart_point_line.py
flet/core/charts/chart_point_shape.py
flet/core/charts/line_chart.py
flet/core/charts/line_chart_data.py
flet/core/charts/line_chart_data_point.py
flet/core/charts/pie_chart.py
flet/core/charts/pie_chart_section.py
flet/core/checkbox.py
flet/core/chip.py
flet/core/circle_avatar.py
flet/core/client_storage.py
flet/core/colors.py
flet/core/column.py
flet_contribute-2024.12.30.1738.dist-info/METADATA
flet_contribute-2024.12.30.1738.dist-info/WHEEL
flet_contribute-2024.12.30.1738.dist-info/entry_points.txt
flet_contribute-2024.12.30.1738.dist-info/RECORD
